nevopy/__init__.py
nevopy/activations.py
nevopy/base_genome.py
nevopy/base_population.py
nevopy/callbacks.py
nevopy/fixed_topology/__init__.py
nevopy/fixed_topology/genomes.py
nevopy/fixed_topology/layers/__init__.py
nevopy/fixed_topology/layers/base_layer.py
nevopy/fixed_topology/layers/mating.py
nevopy/fixed_topology/layers/tf_layers.py
nevopy/genetic_algorithm/__init__.py
nevopy/genetic_algorithm/config.py
nevopy/genetic_algorithm/population.py
nevopy/neat/__init__.py
nevopy/neat/config.py
nevopy/neat/genes.py
nevopy/neat/genomes.py
nevopy/neat/id_handler.py
nevopy/neat/population.py
nevopy/neat/species.py
nevopy/neat/visualization.py
nevopy/processing/__init__.py
nevopy/processing/base_scheduler.py
nevopy/processing/networked_scheduler.py
nevopy/processing/pool_processing.py
nevopy/processing/ray_processing.py
nevopy/processing/serial_processing.py
nevopy/utils/__init__.py
nevopy/utils/deprecation.py
nevopy/utils/utils.py
nevopy/utils/gym_utils/__init__.py
nevopy/utils/gym_utils/callbacks.py
nevopy/utils/gym_utils/fitness_function.py
nevopy/utils/gym_utils/renderers.py
nevopy-0.2.3.dist-info/LICENSE
nevopy-0.2.3.dist-info/METADATA
nevopy-0.2.3.dist-info/WHEEL
nevopy-0.2.3.dist-info/top_level.txt
nevopy-0.2.3.dist-info/RECORD
