Metadata-Version: 2.1
Name: nevopy
Version: 0.2.3
Summary: An open source neuroevolution framework for Python.
Home-page: https://github.com/Talendar/nevopy
Author: Gabriel Guedes Nogueira (Talendar)
Author-email: gabriel.gnogueira@gmail.com
License: MIT License
Download-URL: https://github.com/Talendar/nevopy/releases
Keywords: nevopy neuroevolution evolutionary algorithms machine learning
Platform: UNKNOWN
Classifier: Programming Language :: Python :: 3
Classifier: Programming Language :: Python :: 3 :: Only
Classifier: Programming Language :: Python :: 3.6
Classifier: Programming Language :: Python :: 3.7
Classifier: Programming Language :: Python :: 3.8
Classifier: Programming Language :: Python :: 3.9
Classifier: License :: OSI Approved :: MIT License
Classifier: Operating System :: OS Independent
Classifier: Intended Audience :: Developers
Classifier: Intended Audience :: Education
Classifier: Intended Audience :: Science/Research
Classifier: Topic :: Scientific/Engineering
Classifier: Topic :: Scientific/Engineering :: Mathematics
Classifier: Topic :: Scientific/Engineering :: Artificial Intelligence
Classifier: Topic :: Software Development
Classifier: Topic :: Software Development :: Libraries
Classifier: Topic :: Software Development :: Libraries :: Python Modules
Requires-Python: >=3.6
Requires-Dist: Columnar (~=1.3.1)
Requires-Dist: gym (~=0.17.3)
Requires-Dist: matplotlib (~=3.3.3)
Requires-Dist: networkx (~=2.5)
Requires-Dist: numpy (~=1.19.5)
Requires-Dist: ray (~=1.1.0)
Requires-Dist: tensorflow (~=2.4.0)
